wedeliver_core/__init__.py
wedeliver_core/base.py
wedeliver_core/app_decorators/__init__.py
wedeliver_core/app_decorators/app_entry.py
wedeliver_core/app_decorators/handle_auth.py
wedeliver_core/app_decorators/handle_exceptions.py
wedeliver_core/app_decorators/handle_response.py
wedeliver_core/app_decorators/serializer.py
wedeliver_core/helpers/__init__.py
wedeliver_core/helpers/acl_enum.py
wedeliver_core/helpers/atomic_transactions.py
wedeliver_core/helpers/atomic_transactions_v2.py
wedeliver_core/helpers/auth.py
wedeliver_core/helpers/config.py
wedeliver_core/helpers/enums.py
wedeliver_core/helpers/exceptions.py
wedeliver_core/helpers/fetch_relational_data.py
wedeliver_core/helpers/filters.py
wedeliver_core/helpers/format_exception.py
wedeliver_core/helpers/get_callback.py
wedeliver_core/helpers/get_country_code.py
wedeliver_core/helpers/get_embedded_function.py
wedeliver_core/helpers/get_obj_value.py
wedeliver_core/helpers/get_prefix.py
wedeliver_core/helpers/kafka_producer.py
wedeliver_core/helpers/log_config.py
wedeliver_core/helpers/micro_fetcher.py
wedeliver_core/helpers/notification_center.py
wedeliver_core/helpers/search_function.py
wedeliver_core/helpers/send_sms.py
wedeliver_core/helpers/service_config.py
wedeliver_core/helpers/sql.py
wedeliver_core/helpers/time.py
wedeliver_core/helpers/topics.py
wedeliver_core/helpers/validate_mobile_number.py
wedeliver_core/helpers/validate_parameters.py
wedeliver_core/helpers/amazon/__init__.py
wedeliver_core/helpers/amazon/append_plain_urls_to_list_dict.py
wedeliver_core/helpers/amazon/get_file_url.py
wedeliver_core/helpers/amazon/get_plain_url.py
wedeliver_core/helpers/amazon/get_s3_client.py
wedeliver_core/helpers/database/__init__.py
wedeliver_core/helpers/database/base_model.py
wedeliver_core/helpers/database/log_model.py
wedeliver_core/helpers/kafka_producers/__init__.py
wedeliver_core/helpers/kafka_producers/log_model_changes.py
wedeliver_core-0.6.9.dist-info/METADATA
wedeliver_core-0.6.9.dist-info/WHEEL
wedeliver_core-0.6.9.dist-info/top_level.txt
wedeliver_core-0.6.9.dist-info/RECORD
